{
  "payloads": [
    {
      "creator": "0x57ab7ee15cE5ECacB1aB84EE42D5A9d0d8112922",
      "maximumAccessLevelRequired": 1,
      "state": 3,
      "createdAt": 1753359179,
      "queuedAt": 1753709159,
      "executedAt": 1753795643,
      "cancelledAt": 0,
      "expirationTime": 1756383179,
      "delay": 86400,
      "gracePeriod": 604800,
      "actions": [
        {
          "target": "0x3DFeAbEd49E218F6EB359e4e78cf02284aBA8dE7",
          "withDelegateCall": true,
          "accessLevel": 1,
          "value": "0",
          "signature": "execute()",
          "callData": "0x"
        }
      ],
      "id": 320,
      "chainId": 1,
      "payloadsController": "0xdAbad81aF85554E9ae636395611C58F7eC1aAEc5"
    }
  ],
  "ipfs": {
    "ipfsHash": "QmXvptZvKSpbXu4gKfuTiRMUtF7xcvRWjADYbJVcx1r5c6",
    "description": "\n## Simple Summary\n\nThis proposal aims to add USDe as collateral to the existing sUSDe/Stablecoins emode category to improve capital efficiency and provide a more cohesive borrowing experience for users of Ethena assets on Aave.\n\n## Motivation\n\nCurrently, the sUSDe (Ethena Synthetic USD) has its own e-mode category in Aave, allowing for optimized borrowing for this specific asset. However, USDe, the native stablecoin from Ethena, is not included in this same e-mode category despite being the underlying asset for sUSDe.\n\n### Rationale\n\n- USDe and sUSDe are intrinsically linked, with sUSDe being the staked version of USDe\n- Both assets have similar risk profiles and high correlation\n- Adding USDe as collateral to the same e-mode category would allow users to add USDe exposure while maintaining their leverage.\n- This change would allow borrowers to use either asset as collateral more effectively\n\n## Specification\n\nUSDe will be added as collateral to the sUSDe stablecoin emode (id:2)\n\n| Asset | Current    | Proposed   |\n| ----- | ---------- | ---------- |\n| sUSDe | Collateral | Collateral |\n| USDe  | None       | Collateral |\n| USDC  | Borrowable | Borrowable |\n| USDT  | Borrowable | Borrowable |\n| USDS  | Borrowable | Borrowable |\n\n## References\n\n- Implementation: [AaveV3Ethereum](https://github.com/bgd-labs/aave-proposals-v3/blob/19c0d37a685dbd81c220d3e2a2f13501f53e6d45/src/20250723_AaveV3Ethereum_AddUSDeToTheSUSDeEmodeCategory/AaveV3Ethereum_AddUSDeToTheSUSDeEmodeCategory_20250723.sol)\n- Tests: [AaveV3Ethereum](https://github.com/bgd-labs/aave-proposals-v3/blob/19c0d37a685dbd81c220d3e2a2f13501f53e6d45/src/20250723_AaveV3Ethereum_AddUSDeToTheSUSDeEmodeCategory/AaveV3Ethereum_AddUSDeToTheSUSDeEmodeCategory_20250723.t.sol)\n- Snapshot: Direct-to-AIP\n- [Discussion](https://governance.aave.com/t/direct-to-aip-add-usde-to-the-susde-emode-category/22657)\n\n## Copyright\n\nCopyright and related rights waived via [CC0](https://creativecommons.org/publicdomain/zero/1.0/).\n",
    "title": "Add USDe to the sUSDe emode Category",
    "author": "Aave-Chan Initiative",
    "discussions": "https://governance.aave.com/t/direct-to-aip-add-usde-to-the-susde-emode-category/22657",
    "originalIpfsHash": "0x8e7a70da64e3a8c4f485779aaaa48b9976fff80129aa29815807c8549068354b"
  },
  "proposal": {
    "id": 345,
    "votingDuration": 259200,
    "creationTime": 1753432523,
    "accessLevel": 1,
    "state": 6,
    "queuingTime": 0,
    "ipfsHash": "0x8e7a70da64e3a8c4f485779aaaa48b9976fff80129aa29815807c8549068354b",
    "initialPayloads": [
      {
        "id": 320,
        "chainId": 1,
        "payloadsController": "0xdAbad81aF85554E9ae636395611C58F7eC1aAEc5"
      }
    ],
    "snapshotBlockHash": "0x0000000000000000000000000000000000000000000000000000000000000000",
    "creator": "0x57ab7ee15cE5ECacB1aB84EE42D5A9d0d8112922",
    "canceledAt": 1753432919,
    "votingActivationTime": 0,
    "votingChainId": 137,
    "votingMachineData": {
      "id": 345,
      "forVotes": "0",
      "againstVotes": "0",
      "startTime": 0,
      "endTime": 0,
      "votingClosedAndSentBlockNumber": 0,
      "votingClosedAndSentTimestamp": 0,
      "l1BlockHash": "0x0000000000000000000000000000000000000000000000000000000000000000",
      "strategy": "0xd755F1CA351E989391a5bacDeC8F780dFD76f5d2",
      "sentToGovernance": false,
      "createdBlock": 0,
      "votedInfo": {
        "support": false,
        "votingPower": "0"
      },
      "votingAssets": [
        "0x7Fc66500c84A76Ad7e9c93437bFc5Ac33E2DDaE9",
        "0x4da27a545c0c5B758a6BA100e3a049001de870f5",
        "0xA700b4eB416Be35b2911fd5Dee80678ff64fF6C9"
      ],
      "hasRequiredRoots": false
    },
    "isFinished": true,
    "lastUpdatedTimestamp": 1769300905,
    "cancellationFee": 50000000000000000
  }
}