{
  "payloads": [
    {
      "creator": "0x57ab7ee15cE5ECacB1aB84EE42D5A9d0d8112922",
      "maximumAccessLevelRequired": 1,
      "state": 3,
      "createdAt": 1741960439,
      "queuedAt": 1742311379,
      "executedAt": 1742397827,
      "cancelledAt": 0,
      "expirationTime": 1744984439,
      "delay": 86400,
      "gracePeriod": 604800,
      "actions": [
        {
          "target": "0x50fbD9C93fbF99C38104b1dcAe84cE0d2071b440",
          "withDelegateCall": true,
          "accessLevel": 1,
          "value": "0",
          "signature": "execute()",
          "callData": "0x"
        },
        {
          "target": "0xAf54Cd5e62b995059C1ef507B7de67d403b42ed4",
          "withDelegateCall": true,
          "accessLevel": 1,
          "value": "0",
          "signature": "execute()",
          "callData": "0x"
        },
        {
          "target": "0x89B6d89fb3cFE5c59cb7d972c4DDb81aFC160272",
          "withDelegateCall": true,
          "accessLevel": 1,
          "value": "0",
          "signature": "execute()",
          "callData": "0x"
        }
      ],
      "id": 259,
      "chainId": 1,
      "payloadsController": "0xdAbad81aF85554E9ae636395611C58F7eC1aAEc5"
    },
    {
      "creator": "0x57ab7ee15cE5ECacB1aB84EE42D5A9d0d8112922",
      "maximumAccessLevelRequired": 1,
      "state": 3,
      "createdAt": 1741960626,
      "queuedAt": 1742312381,
      "executedAt": 1742398790,
      "cancelledAt": 0,
      "expirationTime": 1744984626,
      "delay": 86400,
      "gracePeriod": 604800,
      "actions": [
        {
          "target": "0xb7A82d685677A0085f96815a0DC4521BFDFA7156",
          "withDelegateCall": true,
          "accessLevel": 1,
          "value": "0",
          "signature": "execute()",
          "callData": "0x"
        }
      ],
      "id": 72,
      "chainId": 43114,
      "payloadsController": "0x1140CB7CAfAcC745771C2Ea31e7B5C653c5d0B80"
    },
    {
      "creator": "0x57ab7ee15cE5ECacB1aB84EE42D5A9d0d8112922",
      "maximumAccessLevelRequired": 1,
      "state": 3,
      "createdAt": 1741960807,
      "queuedAt": 1742311459,
      "executedAt": 1742397867,
      "cancelledAt": 0,
      "expirationTime": 1744984807,
      "delay": 86400,
      "gracePeriod": 604800,
      "actions": [
        {
          "target": "0xB553Cf1d27C2595524f837F0a8C8736a0Ae70F5F",
          "withDelegateCall": true,
          "accessLevel": 1,
          "value": "0",
          "signature": "execute()",
          "callData": "0x"
        }
      ],
      "id": 70,
      "chainId": 10,
      "payloadsController": "0x0E1a3Af1f9cC76A62eD31eDedca291E63632e7c4"
    },
    {
      "creator": "0x57ab7ee15cE5ECacB1aB84EE42D5A9d0d8112922",
      "maximumAccessLevelRequired": 1,
      "state": 3,
      "createdAt": 1741960994,
      "queuedAt": 1742311778,
      "executedAt": 1742398183,
      "cancelledAt": 0,
      "expirationTime": 1744984994,
      "delay": 86400,
      "gracePeriod": 604800,
      "actions": [
        {
          "target": "0x73e117f3D7F02a2e69E851203eBcdFfacb6263CD",
          "withDelegateCall": true,
          "accessLevel": 1,
          "value": "0",
          "signature": "execute()",
          "callData": "0x"
        }
      ],
      "id": 80,
      "chainId": 42161,
      "payloadsController": "0x89644CA1bB8064760312AE4F03ea41b05dA3637C"
    },
    {
      "creator": "0x3Cbded22F878aFC8d39dCD744d3Fe62086B76193",
      "maximumAccessLevelRequired": 1,
      "state": 3,
      "createdAt": 1741963211,
      "queuedAt": 1742311536,
      "executedAt": 1742399101,
      "cancelledAt": 0,
      "expirationTime": 1744987211,
      "delay": 86400,
      "gracePeriod": 604800,
      "actions": [
        {
          "target": "0x6668e20492dbBa0494019C9D333BeE456928520B",
          "withDelegateCall": true,
          "accessLevel": 1,
          "value": "0",
          "signature": "execute()",
          "callData": "0x"
        }
      ],
      "id": 36,
      "chainId": 1088,
      "payloadsController": "0x2233F8A66A728FBa6E1dC95570B25360D07D5524"
    },
    {
      "creator": "0x57ab7ee15cE5ECacB1aB84EE42D5A9d0d8112922",
      "maximumAccessLevelRequired": 1,
      "state": 3,
      "createdAt": 1741961485,
      "queuedAt": 1742311563,
      "executedAt": 1742397973,
      "cancelledAt": 0,
      "expirationTime": 1744985485,
      "delay": 86400,
      "gracePeriod": 604800,
      "actions": [
        {
          "target": "0xBda7dF5939B5eD34e52E71678A16A39db506b475",
          "withDelegateCall": true,
          "accessLevel": 1,
          "value": "0",
          "signature": "execute()",
          "callData": "0x"
        }
      ],
      "id": 62,
      "chainId": 8453,
      "payloadsController": "0x2DC219E716793fb4b21548C0f009Ba3Af753ab01"
    },
    {
      "creator": "0x57ab7ee15cE5ECacB1aB84EE42D5A9d0d8112922",
      "maximumAccessLevelRequired": 1,
      "state": 3,
      "createdAt": 1741961645,
      "queuedAt": 1742313510,
      "executedAt": 1742401090,
      "cancelledAt": 0,
      "expirationTime": 1744985645,
      "delay": 86400,
      "gracePeriod": 604800,
      "actions": [
        {
          "target": "0x1Fc0450B42cd137e4fFc06b7b8c102D246Af2a6d",
          "withDelegateCall": true,
          "accessLevel": 1,
          "value": "0",
          "signature": "execute()",
          "callData": "0x"
        }
      ],
      "id": 47,
      "chainId": 100,
      "payloadsController": "0x9A1F491B86D09fC1484b5fab10041B189B60756b"
    },
    {
      "creator": "0x57ab7ee15cE5ECacB1aB84EE42D5A9d0d8112922",
      "maximumAccessLevelRequired": 1,
      "state": 3,
      "createdAt": 1741961768,
      "queuedAt": 1742312284,
      "executedAt": 1742552842,
      "cancelledAt": 0,
      "expirationTime": 1744985768,
      "delay": 86400,
      "gracePeriod": 604800,
      "actions": [
        {
          "target": "0x65dAc98e5D04547d7E5ac994eabeA0322936F7ba",
          "withDelegateCall": true,
          "accessLevel": 1,
          "value": "0",
          "signature": "execute()",
          "callData": "0x"
        }
      ],
      "id": 37,
      "chainId": 534352,
      "payloadsController": "0x6b6B41c0f8C223715f712BE83ceC3c37bbfDC3fE"
    },
    {
      "creator": "0x57ab7ee15cE5ECacB1aB84EE42D5A9d0d8112922",
      "maximumAccessLevelRequired": 1,
      "state": 3,
      "createdAt": 1741962982,
      "queuedAt": 1742312360,
      "executedAt": 1742398769,
      "cancelledAt": 0,
      "expirationTime": 1744986982,
      "delay": 86400,
      "gracePeriod": 604800,
      "actions": [
        {
          "target": "0xE38C9AC9f167deAa8DB30b98a2C5E109c88CBb00",
          "withDelegateCall": true,
          "accessLevel": 1,
          "value": "0",
          "signature": "execute()",
          "callData": "0x"
        }
      ],
      "id": 35,
      "chainId": 56,
      "payloadsController": "0xE5EF2Dd06755A97e975f7E282f828224F2C3e627"
    },
    {
      "creator": "0x02fEb744cA516FD6E41D940Ae2d0F7Cb6FCB1ac3",
      "maximumAccessLevelRequired": 1,
      "state": 3,
      "createdAt": 1741809951,
      "queuedAt": 1742312304,
      "executedAt": 1742399345,
      "cancelledAt": 0,
      "expirationTime": 1744833951,
      "delay": 86400,
      "gracePeriod": 604800,
      "actions": [
        {
          "target": "0xeD995f040Ba5c606D6945400a29087dB35209314",
          "withDelegateCall": true,
          "accessLevel": 1,
          "value": "0",
          "signature": "execute()",
          "callData": "0x"
        }
      ],
      "id": 19,
      "chainId": 324,
      "payloadsController": "0x2E79349c3F5e4751E87b966812C9E65E805996F1"
    }
  ],
  "ipfs": {
    "ipfsHash": "QmcTZdNwuBJUGVvnmnpKLWUKSkrG2D1udUUUtwvmSkB3s9",
    "description": "\n## Simple Summary\n\nIn light of recent market changes, Chaos Labs recommends setting the target borrow rate for most stablecoins to 6.50%. These changes would be implemented via the direct-to-AIP process.\n\n## Motivation\n\nThe utilization for stablecoins across Aave has resumed falling after a brief improvement following the last IR curve adjustment, calling for a further reduction in target rates to better align with the market-priced interest rate.\n\nA closer look at the largest stablecoin markets indicates that borrow rates have stabilized between 6% and 8%.\n\nAs a result, we recommend setting the target rate for all stablecoins to 6.5%;\n\nPlease note that GHO, USDS, and pyUSD are managed separately and, thus, are not included in these recommendations.\n\n## Specification\n\n| Protocol | Instance         | Asset  | **Current Slope1** | **Rec. Slope1** |\n| -------- | ---------------- | ------ | ------------------ | --------------- |\n| Aave V3  | Ethereum Core    | USDC   | 8.50%              | 6.50%           |\n| Aave V3  | Ethereum Core    | DAI    | 8.50%              | 6.50%           |\n| Aave V3  | Ethereum Core    | USDT   | 8.50%              | 6.50%           |\n| Aave V3  | Ethereum Core    | LUSD   | 8.50%              | 6.50%           |\n| Aave V3  | Ethereum Core    | FRAX   | 8.50%              | 6.50%           |\n| Aave V3  | Ethereum Core    | crvUSD | 8.50%              | 6.50%           |\n| Aave V3  | Ethereum Core    | USDe   | 8.50%              | 6.50%           |\n| Aave V3  | Ethereum Prime   | USDC   | 8.50%              | 6.50%           |\n| Aave V3  | Ethereum EtherFi | USDC   | 8.50%              | 6.50%           |\n| Aave V3  | Ethereum EtherFi | FRAX   | 8.50%              | 6.50%           |\n| Aave V3  | Arbitrum         | DAI    | 9%                 | 6.50%           |\n| Aave V3  | Arbitrum         | USDT   | 9%                 | 6.50%           |\n| Aave V3  | Arbitrum         | LUSD   | 9%                 | 6.50%           |\n| Aave V3  | Arbitrum         | USDC   | 9%                 | 6.50%           |\n| Aave V3  | Arbitrum         | FRAX   | 9%                 | 6.50%           |\n| Aave V3  | Optimism         | DAI    | 9%                 | 6.50%           |\n| Aave V3  | Optimism         | USDT   | 9%                 | 6.50%           |\n| Aave V3  | Optimism         | sUSD   | 9%                 | 6.50%           |\n| Aave V3  | Optimism         | LUSD   | 9%                 | 6.50%           |\n| Aave V3  | Optimism         | USDC   | 9%                 | 6.50%           |\n| Aave V3  | Base             | USDC   | 9%                 | 6.50%           |\n| Aave V3  | Metis            | m.DAI  | 9.50%              | 6.50%           |\n| Aave V3  | Metis            | m.USDC | 9.50%              | 6.50%           |\n| Aave V3  | Metis            | m.USDT | 9.50%              | 6.50%           |\n| Aave V3  | Avalanche        | DAI.e  | 8.50%              | 6.50%           |\n| Aave V3  | Avalanche        | USDC   | 8.50%              | 6.50%           |\n| Aave V3  | Avalanche        | USDt   | 8.50%              | 6.50%           |\n| Aave V3  | Avalanche        | FRAX   | 8.50%              | 6.50%           |\n| Aave V3  | Avalanche        | AUSD   | 8.50%              | 6.50%           |\n| Aave V3  | Gnosis           | WXDAI  | 9%                 | 6.50%           |\n| Aave V3  | Gnosis           | EURe   | 9%                 | 6.50%           |\n| Aave V3  | Gnosis           | USDC.e | 9%                 | 6.50%           |\n| Aave V3  | BNB              | USDC   | 8.50%              | 6.50%           |\n| Aave V3  | BNB              | USDT   | 8.50%              | 6.50%           |\n| Aave V3  | BNB              | FDUSD  | 8.50%              | 6.50%           |\n| Aave V3  | Scroll           | USDC   | 8.50%              | 6.50%           |\n| Aave V3  | ZkSync           | USDC   | 8.50%              | 6.50%           |\n| Aave V3  | ZkSync           | USDT   | 8.50%              | 6.50%           |\n\n## References\n\n- Implementation: [AaveV3Ethereum](https://github.com/bgd-labs/aave-proposals-v3/blob/78b4d81bddc1978b7807d39859b806883e087d15/src/20250312_Multi_StablecoinsInterestRateCurveUpdate/AaveV3Ethereum_StablecoinsInterestRateCurveUpdate_20250312.sol), [AaveV3EthereumLido](https://github.com/bgd-labs/aave-proposals-v3/blob/78b4d81bddc1978b7807d39859b806883e087d15/src/20250312_Multi_StablecoinsInterestRateCurveUpdate/AaveV3EthereumLido_StablecoinsInterestRateCurveUpdate_20250312.sol), [AaveV3EthereumEtherFi](https://github.com/bgd-labs/aave-proposals-v3/blob/78b4d81bddc1978b7807d39859b806883e087d15/src/20250312_Multi_StablecoinsInterestRateCurveUpdate/AaveV3EthereumEtherFi_StablecoinsInterestRateCurveUpdate_20250312.sol), [AaveV3Polygon](https://github.com/bgd-labs/aave-proposals-v3/blob/78b4d81bddc1978b7807d39859b806883e087d15/src/20250312_Multi_StablecoinsInterestRateCurveUpdate/AaveV3Polygon_StablecoinsInterestRateCurveUpdate_20250312.sol), [AaveV3Avalanche](https://github.com/bgd-labs/aave-proposals-v3/blob/78b4d81bddc1978b7807d39859b806883e087d15/src/20250312_Multi_StablecoinsInterestRateCurveUpdate/AaveV3Avalanche_StablecoinsInterestRateCurveUpdate_20250312.sol), [AaveV3Optimism](https://github.com/bgd-labs/aave-proposals-v3/blob/78b4d81bddc1978b7807d39859b806883e087d15/src/20250312_Multi_StablecoinsInterestRateCurveUpdate/AaveV3Optimism_StablecoinsInterestRateCurveUpdate_20250312.sol), [AaveV3Arbitrum](https://github.com/bgd-labs/aave-proposals-v3/blob/78b4d81bddc1978b7807d39859b806883e087d15/src/20250312_Multi_StablecoinsInterestRateCurveUpdate/AaveV3Arbitrum_StablecoinsInterestRateCurveUpdate_20250312.sol), [AaveV3Metis](https://github.com/bgd-labs/aave-proposals-v3/blob/78b4d81bddc1978b7807d39859b806883e087d15/src/20250312_Multi_StablecoinsInterestRateCurveUpdate/AaveV3Metis_StablecoinsInterestRateCurveUpdate_20250312.sol), [AaveV3Base](https://github.com/bgd-labs/aave-proposals-v3/blob/78b4d81bddc1978b7807d39859b806883e087d15/src/20250312_Multi_StablecoinsInterestRateCurveUpdate/AaveV3Base_StablecoinsInterestRateCurveUpdate_20250312.sol), [AaveV3Gnosis](https://github.com/bgd-labs/aave-proposals-v3/blob/78b4d81bddc1978b7807d39859b806883e087d15/src/20250312_Multi_StablecoinsInterestRateCurveUpdate/AaveV3Gnosis_StablecoinsInterestRateCurveUpdate_20250312.sol), [AaveV3Scroll](https://github.com/bgd-labs/aave-proposals-v3/blob/78b4d81bddc1978b7807d39859b806883e087d15/src/20250312_Multi_StablecoinsInterestRateCurveUpdate/AaveV3Scroll_StablecoinsInterestRateCurveUpdate_20250312.sol), [AaveV3BNB](https://github.com/bgd-labs/aave-proposals-v3/blob/78b4d81bddc1978b7807d39859b806883e087d15/src/20250312_Multi_StablecoinsInterestRateCurveUpdate/AaveV3BNB_StablecoinsInterestRateCurveUpdate_20250312.sol), [AaveV3ZkSync](https://github.com/bgd-labs/aave-proposals-v3/blob/78b4d81bddc1978b7807d39859b806883e087d15/zksync/src/20250312_Multi_StablecoinsInterestRateCurveUpdate/AaveV3ZkSync_StablecoinsInterestRateCurveUpdate_20250312.sol)\n- Tests: [AaveV3Ethereum](https://github.com/bgd-labs/aave-proposals-v3/blob/78b4d81bddc1978b7807d39859b806883e087d15/src/20250312_Multi_StablecoinsInterestRateCurveUpdate/AaveV3Ethereum_StablecoinsInterestRateCurveUpdate_20250312.t.sol), [AaveV3EthereumLido](https://github.com/bgd-labs/aave-proposals-v3/blob/78b4d81bddc1978b7807d39859b806883e087d15/src/20250312_Multi_StablecoinsInterestRateCurveUpdate/AaveV3EthereumLido_StablecoinsInterestRateCurveUpdate_20250312.t.sol), [AaveV3EthereumEtherFi](https://github.com/bgd-labs/aave-proposals-v3/blob/78b4d81bddc1978b7807d39859b806883e087d15/src/20250312_Multi_StablecoinsInterestRateCurveUpdate/AaveV3EthereumEtherFi_StablecoinsInterestRateCurveUpdate_20250312.t.sol), [AaveV3Polygon](https://github.com/bgd-labs/aave-proposals-v3/blob/78b4d81bddc1978b7807d39859b806883e087d15/src/20250312_Multi_StablecoinsInterestRateCurveUpdate/AaveV3Polygon_StablecoinsInterestRateCurveUpdate_20250312.t.sol), [AaveV3Avalanche](https://github.com/bgd-labs/aave-proposals-v3/blob/78b4d81bddc1978b7807d39859b806883e087d15/src/20250312_Multi_StablecoinsInterestRateCurveUpdate/AaveV3Avalanche_StablecoinsInterestRateCurveUpdate_20250312.t.sol), [AaveV3Optimism](https://github.com/bgd-labs/aave-proposals-v3/blob/78b4d81bddc1978b7807d39859b806883e087d15/src/20250312_Multi_StablecoinsInterestRateCurveUpdate/AaveV3Optimism_StablecoinsInterestRateCurveUpdate_20250312.t.sol), [AaveV3Arbitrum](https://github.com/bgd-labs/aave-proposals-v3/blob/78b4d81bddc1978b7807d39859b806883e087d15/src/20250312_Multi_StablecoinsInterestRateCurveUpdate/AaveV3Arbitrum_StablecoinsInterestRateCurveUpdate_20250312.t.sol), [AaveV3Metis](https://github.com/bgd-labs/aave-proposals-v3/blob/78b4d81bddc1978b7807d39859b806883e087d15/src/20250312_Multi_StablecoinsInterestRateCurveUpdate/AaveV3Metis_StablecoinsInterestRateCurveUpdate_20250312.t.sol), [AaveV3Base](https://github.com/bgd-labs/aave-proposals-v3/blob/78b4d81bddc1978b7807d39859b806883e087d15/src/20250312_Multi_StablecoinsInterestRateCurveUpdate/AaveV3Base_StablecoinsInterestRateCurveUpdate_20250312.t.sol), [AaveV3Gnosis](https://github.com/bgd-labs/aave-proposals-v3/blob/78b4d81bddc1978b7807d39859b806883e087d15/src/20250312_Multi_StablecoinsInterestRateCurveUpdate/AaveV3Gnosis_StablecoinsInterestRateCurveUpdate_20250312.t.sol), [AaveV3Scroll](https://github.com/bgd-labs/aave-proposals-v3/blob/78b4d81bddc1978b7807d39859b806883e087d15/src/20250312_Multi_StablecoinsInterestRateCurveUpdate/AaveV3Scroll_StablecoinsInterestRateCurveUpdate_20250312.t.sol), [AaveV3BNB](https://github.com/bgd-labs/aave-proposals-v3/blob/78b4d81bddc1978b7807d39859b806883e087d15/src/20250312_Multi_StablecoinsInterestRateCurveUpdate/AaveV3BNB_StablecoinsInterestRateCurveUpdate_20250312.t.sol), [AaveV3ZkSync](https://github.com/bgd-labs/aave-proposals-v3/blob/78b4d81bddc1978b7807d39859b806883e087d15/zksync/src/20250312_Multi_StablecoinsInterestRateCurveUpdate/AaveV3ZkSync_StablecoinsInterestRateCurveUpdate_20250312.t.sol)\n- Snapshot: Direct-to-AIP\n- [Discussion](https://governance.aave.com/t/arfc-stablecoin-interest-rate-curve-update-03-04-2025/21269)\n\n## Copyright\n\nCopyright and related rights waived via [CC0](https://creativecommons.org/publicdomain/zero/1.0/).\n",
    "title": "Stablecoins Interest Rate Curve Update",
    "author": "Aave Chan Initiative",
    "discussions": "https://governance.aave.com/t/arfc-stablecoin-interest-rate-curve-update-03-04-2025/21269",
    "originalIpfsHash": "0xd1c8efdc310bd2fdd2d4f00fdeb9c01758078f56d24218c778d58132f11f1104"
  },
  "proposal": {
    "id": 271,
    "votingDuration": 259200,
    "creationTime": 1741963331,
    "accessLevel": 1,
    "state": 4,
    "queuingTime": 1742311367,
    "ipfsHash": "0xd1c8efdc310bd2fdd2d4f00fdeb9c01758078f56d24218c778d58132f11f1104",
    "initialPayloads": [
      {
        "id": 259,
        "chainId": 1,
        "payloadsController": "0xdAbad81aF85554E9ae636395611C58F7eC1aAEc5"
      },
      {
        "id": 72,
        "chainId": 43114,
        "payloadsController": "0x1140CB7CAfAcC745771C2Ea31e7B5C653c5d0B80"
      },
      {
        "id": 70,
        "chainId": 10,
        "payloadsController": "0x0E1a3Af1f9cC76A62eD31eDedca291E63632e7c4"
      },
      {
        "id": 80,
        "chainId": 42161,
        "payloadsController": "0x89644CA1bB8064760312AE4F03ea41b05dA3637C"
      },
      {
        "id": 36,
        "chainId": 1088,
        "payloadsController": "0x2233F8A66A728FBa6E1dC95570B25360D07D5524"
      },
      {
        "id": 62,
        "chainId": 8453,
        "payloadsController": "0x2DC219E716793fb4b21548C0f009Ba3Af753ab01"
      },
      {
        "id": 47,
        "chainId": 100,
        "payloadsController": "0x9A1F491B86D09fC1484b5fab10041B189B60756b"
      },
      {
        "id": 37,
        "chainId": 534352,
        "payloadsController": "0x6b6B41c0f8C223715f712BE83ceC3c37bbfDC3fE"
      },
      {
        "id": 35,
        "chainId": 56,
        "payloadsController": "0xE5EF2Dd06755A97e975f7E282f828224F2C3e627"
      },
      {
        "id": 19,
        "chainId": 324,
        "payloadsController": "0x2E79349c3F5e4751E87b966812C9E65E805996F1"
      }
    ],
    "snapshotBlockHash": "0x0d8b13bea7bccd555afdf4a85f175700cb95aa1dc0d3a823b55e2451a57aaf56",
    "creator": "0x57ab7ee15cE5ECacB1aB84EE42D5A9d0d8112922",
    "canceledAt": 0,
    "votingActivationTime": 1742049755,
    "votingChainId": 137,
    "votingMachineData": {
      "id": 271,
      "forVotes": "680962956656929326015173",
      "againstVotes": "0",
      "startTime": 1742051037,
      "endTime": 1742310237,
      "votingClosedAndSentBlockNumber": 69203781,
      "votingClosedAndSentTimestamp": 1742310250,
      "l1BlockHash": "0x0d8b13bea7bccd555afdf4a85f175700cb95aa1dc0d3a823b55e2451a57aaf56",
      "strategy": "0x59e6CAD5d7E7b9A26a45a1d1E74C7aF008170042",
      "sentToGovernance": true,
      "createdBlock": 69083267,
      "votedInfo": {
        "support": false,
        "votingPower": "0"
      },
      "votingAssets": [
        "0x7Fc66500c84A76Ad7e9c93437bFc5Ac33E2DDaE9",
        "0x4da27a545c0c5B758a6BA100e3a049001de870f5",
        "0xA700b4eB416Be35b2911fd5Dee80678ff64fF6C9"
      ],
      "hasRequiredRoots": true
    },
    "isFinished": true,
    "lastUpdatedTimestamp": 1743843987,
    "cancellationFee": 50000000000000000
  }
}