{
  "payloads": [
    {
      "creator": "0x3Cbded22F878aFC8d39dCD744d3Fe62086B76193",
      "maximumAccessLevelRequired": 1,
      "state": 3,
      "createdAt": 1723798308,
      "queuedAt": 1724147009,
      "executedAt": 1724234256,
      "cancelledAt": 0,
      "expirationTime": 1726822308,
      "delay": 86400,
      "gracePeriod": 604800,
      "actions": [
        {
          "target": "0x0eC1A3d247843b688b354BFF80444B952a08C663",
          "withDelegateCall": true,
          "accessLevel": 1,
          "value": "0",
          "signature": "execute()",
          "callData": "0x"
        }
      ],
      "id": 23,
      "chainId": 1088,
      "payloadsController": "0x2233F8A66A728FBa6E1dC95570B25360D07D5524"
    }
  ],
  "ipfs": {
    "ipfsHash": "QmcC844vYq3mXvc9DNibbS2ki2o39KWy2t6S3zv23ueFFB",
    "description": "\n## Simple Summary\n\nThis proposal recommends enabling Metis token as collateral on Aave V3 within the Metis Chain\n\n## Motivation\n\nIntegrating Metis as collateral positions Aave as a key player in the Metis ecosystem, alongside upcoming incentives for builders and new projects. This move is anticipated to bolster Aave’s prominence as the leading lending platform on Metis Chain.\n\n## Specification\n\nThe proposed risk parameters for incorporating Metis as collateral are outlined below following @ChaosLabs TEMP CHECK recommendation:\n\n| Parameter                  | Value  |\n| -------------------------- | ------ |\n| Isolation Mode             | Yes    |\n| Borrowable                 | Yes    |\n| Collateral Enabled         | Yes    |\n| Debt Ceiling               | $1M    |\n| Loan to Value (LTV)        | 30.00% |\n| Liquidation Threshold (LT) | 40.00% |\n| Liquidation Bonus          | 10.00% |\n| Liquidation Protocol Fee   | 10.00% |\n\n## References\n\n- Implementation: [AaveV3Metis](https://github.com/bgd-labs/aave-proposals-v3/blob/7e9aaa019afed78f36b3f87c3c8c1bbc069053a5/src/20240814_AaveV3Metis_EnableMetisAsCollateralOnMetisChain/AaveV3Metis_EnableMetisAsCollateralOnMetisChain_20240814.sol)\n- Tests: [AaveV3Metis](https://github.com/bgd-labs/aave-proposals-v3/blob/7e9aaa019afed78f36b3f87c3c8c1bbc069053a5/src/20240814_AaveV3Metis_EnableMetisAsCollateralOnMetisChain/AaveV3Metis_EnableMetisAsCollateralOnMetisChain_20240814.t.sol)\n- [Snapshot](https://snapshot.org/#/aave.eth/proposal/0x2e15c7011a6696de1be8fb3476db30395225eb533f849b63bdbff2b33a605ffd)\n- [Discussion](https://governance.aave.com/t/arfc-enable-metis-as-collateral-on-metis-chain/16658)\n\n## Copyright\n\nCopyright and related rights waived via [CC0](https://creativecommons.org/publicdomain/zero/1.0/).\n",
    "title": "Enable Metis as Collateral on Metis Chain",
    "author": "Aave Chan Initiative",
    "discussions": "https://governance.aave.com/t/arfc-enable-metis-as-collateral-on-metis-chain/16658",
    "snapshot": "https://snapshot.org/#/aave.eth/proposal/0x2e15c7011a6696de1be8fb3476db30395225eb533f849b63bdbff2b33a605ffd",
    "originalIpfsHash": "0xcdd44ece79347739c5bd2c69e16f9ddd462f073aa4e0533342a3a3ec7c71d136"
  },
  "proposal": {
    "id": 152,
    "votingDuration": 259200,
    "creationTime": 1723798763,
    "accessLevel": 1,
    "state": 4,
    "queuingTime": 1724146823,
    "ipfsHash": "0xcdd44ece79347739c5bd2c69e16f9ddd462f073aa4e0533342a3a3ec7c71d136",
    "initialPayloads": [
      {
        "id": 23,
        "chainId": 1088,
        "payloadsController": "0x2233F8A66A728FBa6E1dC95570B25360D07D5524"
      }
    ],
    "snapshotBlockHash": "0x7b031c3006e5df1b181e297e8911abec6fde5668b6115c258945e7644b38ded8",
    "creator": "0x57ab7ee15cE5ECacB1aB84EE42D5A9d0d8112922",
    "canceledAt": 0,
    "votingActivationTime": 1723885187,
    "votingChainId": 137,
    "votingMachineData": {
      "id": 152,
      "forVotes": "802917045283057472230977",
      "againstVotes": "0",
      "startTime": 1723886327,
      "endTime": 1724145527,
      "votingClosedAndSentBlockNumber": 60814796,
      "votingClosedAndSentTimestamp": 1724145536,
      "l1BlockHash": "0x7b031c3006e5df1b181e297e8911abec6fde5668b6115c258945e7644b38ded8",
      "strategy": "0x59e6CAD5d7E7b9A26a45a1d1E74C7aF008170042",
      "sentToGovernance": true,
      "createdBlock": 60694293,
      "votedInfo": {
        "support": false,
        "votingPower": "0"
      },
      "votingAssets": [
        "0x7Fc66500c84A76Ad7e9c93437bFc5Ac33E2DDaE9",
        "0x4da27a545c0c5B758a6BA100e3a049001de870f5",
        "0xA700b4eB416Be35b2911fd5Dee80678ff64fF6C9"
      ],
      "hasRequiredRoots": true
    },
    "isFinished": true,
    "lastUpdatedTimestamp": 1725041288,
    "cancellationFee": 50000000000000000
  }
}