{
  "payloads": [
    {
      "creator": "0x57ab7ee15cE5ECacB1aB84EE42D5A9d0d8112922",
      "maximumAccessLevelRequired": 1,
      "state": 3,
      "createdAt": 1712350655,
      "queuedAt": 1712699687,
      "executedAt": 1712786111,
      "cancelledAt": 0,
      "expirationTime": 1715374655,
      "delay": 86400,
      "gracePeriod": 604800,
      "actions": [
        {
          "target": "0xd56232B949Dd7E70E95Bb99514Eaf9Dba160d042",
          "withDelegateCall": true,
          "accessLevel": 1,
          "value": "0",
          "signature": "execute()",
          "callData": "0x"
        }
      ],
      "id": 98,
      "chainId": 1,
      "payloadsController": "0xdAbad81aF85554E9ae636395611C58F7eC1aAEc5"
    },
    {
      "creator": "0x57ab7ee15cE5ECacB1aB84EE42D5A9d0d8112922",
      "maximumAccessLevelRequired": 1,
      "state": 3,
      "createdAt": 1712350731,
      "queuedAt": 1712700735,
      "executedAt": 1712787169,
      "cancelledAt": 0,
      "expirationTime": 1715374731,
      "delay": 86400,
      "gracePeriod": 604800,
      "actions": [
        {
          "target": "0x22b2d204cbBD33dbddf37a63795E3c7F280b56b2",
          "withDelegateCall": true,
          "accessLevel": 1,
          "value": "0",
          "signature": "execute()",
          "callData": "0x"
        }
      ],
      "id": 51,
      "chainId": 137,
      "payloadsController": "0x401B5D0294E23637c18fcc38b1Bca814CDa2637C"
    },
    {
      "creator": "0x57ab7ee15cE5ECacB1aB84EE42D5A9d0d8112922",
      "maximumAccessLevelRequired": 1,
      "state": 3,
      "createdAt": 1712350797,
      "queuedAt": 1712700046,
      "executedAt": 1712786455,
      "cancelledAt": 0,
      "expirationTime": 1715374797,
      "delay": 86400,
      "gracePeriod": 604800,
      "actions": [
        {
          "target": "0x54Bdd028Cf5CDB252990093AccEdAf7995E54EF6",
          "withDelegateCall": true,
          "accessLevel": 1,
          "value": "0",
          "signature": "execute()",
          "callData": "0x"
        }
      ],
      "id": 22,
      "chainId": 43114,
      "payloadsController": "0x1140CB7CAfAcC745771C2Ea31e7B5C653c5d0B80"
    },
    {
      "creator": "0x57ab7ee15cE5ECacB1aB84EE42D5A9d0d8112922",
      "maximumAccessLevelRequired": 1,
      "state": 3,
      "createdAt": 1712350879,
      "queuedAt": 1712699771,
      "executedAt": 1712786175,
      "cancelledAt": 0,
      "expirationTime": 1715374879,
      "delay": 86400,
      "gracePeriod": 604800,
      "actions": [
        {
          "target": "0x11b8cEB0D53c3810959be617B5C22FA63E2181aC",
          "withDelegateCall": true,
          "accessLevel": 1,
          "value": "0",
          "signature": "execute()",
          "callData": "0x"
        }
      ],
      "id": 24,
      "chainId": 10,
      "payloadsController": "0x0E1a3Af1f9cC76A62eD31eDedca291E63632e7c4"
    },
    {
      "creator": "0x57ab7ee15cE5ECacB1aB84EE42D5A9d0d8112922",
      "maximumAccessLevelRequired": 1,
      "state": 3,
      "createdAt": 1712350993,
      "queuedAt": 1712700003,
      "executedAt": 1712786405,
      "cancelledAt": 0,
      "expirationTime": 1715374993,
      "delay": 86400,
      "gracePeriod": 604800,
      "actions": [
        {
          "target": "0x057A200E6ceD7a4447f7da70e9815D62019C5544",
          "withDelegateCall": true,
          "accessLevel": 1,
          "value": "0",
          "signature": "execute()",
          "callData": "0x"
        }
      ],
      "id": 23,
      "chainId": 42161,
      "payloadsController": "0x89644CA1bB8064760312AE4F03ea41b05dA3637C"
    },
    {
      "creator": "0x57ab7ee15cE5ECacB1aB84EE42D5A9d0d8112922",
      "maximumAccessLevelRequired": 1,
      "state": 3,
      "createdAt": 1712351043,
      "queuedAt": 1712699863,
      "executedAt": 1712786271,
      "cancelledAt": 0,
      "expirationTime": 1715375043,
      "delay": 86400,
      "gracePeriod": 604800,
      "actions": [
        {
          "target": "0x5D9584E01Cbde091E66F9444F243e4befAad38B4",
          "withDelegateCall": true,
          "accessLevel": 1,
          "value": "0",
          "signature": "execute()",
          "callData": "0x"
        }
      ],
      "id": 16,
      "chainId": 8453,
      "payloadsController": "0x2DC219E716793fb4b21548C0f009Ba3Af753ab01"
    },
    {
      "creator": "0x57ab7ee15cE5ECacB1aB84EE42D5A9d0d8112922",
      "maximumAccessLevelRequired": 1,
      "state": 3,
      "createdAt": 1712351120,
      "queuedAt": 1712699970,
      "executedAt": 1712786385,
      "cancelledAt": 0,
      "expirationTime": 1715375120,
      "delay": 86400,
      "gracePeriod": 604800,
      "actions": [
        {
          "target": "0x1B8f08D90076c1E0D9e92cb66eD99f9E77dCe2cb",
          "withDelegateCall": true,
          "accessLevel": 1,
          "value": "0",
          "signature": "execute()",
          "callData": "0x"
        }
      ],
      "id": 12,
      "chainId": 100,
      "payloadsController": "0x9A1F491B86D09fC1484b5fab10041B189B60756b"
    },
    {
      "creator": "0x57ab7ee15cE5ECacB1aB84EE42D5A9d0d8112922",
      "maximumAccessLevelRequired": 1,
      "state": 3,
      "createdAt": 1712351161,
      "queuedAt": 1712699965,
      "executedAt": 1712786373,
      "cancelledAt": 0,
      "expirationTime": 1715375161,
      "delay": 86400,
      "gracePeriod": 604800,
      "actions": [
        {
          "target": "0xE2593fA0709C80fE48ac163d0f859DEAE5CF0747",
          "withDelegateCall": true,
          "accessLevel": 1,
          "value": "0",
          "signature": "execute()",
          "callData": "0x"
        }
      ],
      "id": 10,
      "chainId": 56,
      "payloadsController": "0xE5EF2Dd06755A97e975f7E282f828224F2C3e627"
    },
    {
      "creator": "0x3Cbded22F878aFC8d39dCD744d3Fe62086B76193",
      "maximumAccessLevelRequired": 1,
      "state": 3,
      "createdAt": 1712351294,
      "queuedAt": 1712700512,
      "executedAt": 1712821799,
      "cancelledAt": 0,
      "expirationTime": 1715375294,
      "delay": 86400,
      "gracePeriod": 604800,
      "actions": [
        {
          "target": "0x1C3D81Af0bF0a6558B891F51BA708A9de9A92cC1",
          "withDelegateCall": true,
          "accessLevel": 1,
          "value": "0",
          "signature": "execute()",
          "callData": "0x"
        }
      ],
      "id": 8,
      "chainId": 534352,
      "payloadsController": "0x6b6B41c0f8C223715f712BE83ceC3c37bbfDC3fE"
    }
  ],
  "ipfs": {
    "ipfsHash": "QmR7Z2WPhbfBW5nWEfwPXsGQCMrYwtFsSLjjtAJmYL455W",
    "description": "\n## Simple Summary\n\nReduce stablecoin LTs and LTVs across all markets.\n\n## Motivation\n\nIn response to the volatility risks highlighted by the UNI incident on Compound, this proposal aims to mitigate theoretical debt asset volatility by proposing a reduction in collateral asset borrowing power for stablecoins. While the UNI debacle was attributed to inadequate dual-bounded fallback oracle logic, a property not employed by Aave, leading to mispriced UNI debt and subsequent arbitrage activities, the observed upward volatility in longer-tailed assets suggests a prevailing “risk-on” market sentiment. Therefore, we advocate for minimizing borrowing power concerning shorting these assets to prevent potential short squeezes and liquidation shortfalls. Subsequent recommendations will address borrow cap reductions for relevant long-tailed assets, which generate minimal revenue relative to the theoretical risks, especially in edge-case scenarios. Additionally, presently only 2.4%, 3.7% and 5.8% of supplied DAI, USDT and USDC on Ethereum are being utilized as collateral, indicating the generalized lack of demand (and thus revenue).\n\n## Specification\n\n| Assets | Chain     | Current LT | Recommended LT | Current LTV | Recommended LTV |\n| ------ | --------- | ---------- | -------------- | ----------- | --------------- |\n| USDC   | Arbitrum  | 80%        | 79%            | 77%         | 76%             |\n| USDT   | Arbitrum  | 80%        | 79%            | 77%         | 76%             |\n| DAI    | Arbitrum  | 82%        | 79%            | 77%         | 76%             |\n| USDC.e | Arbitrum  | 80%        | 79%            | 77%         | 76%             |\n| USDC   | Avalanche | 86.25%     | 85%            | 82.5%       | 80%             |\n| USDT   | Avalanche | 80%        | 78%            | 77%         | 75%             |\n| DAI    | Avalanche | 82%        | 80%            | 75%         | -               |\n| USDC   | BNBChain  | 80%        | 79%            | 77%         | 76%             |\n| USDT   | BNBChain  | 80%        | 79%            | 77%         | 76%             |\n| USDC   | Base      | 80%        | 79%            | 77%         | 76%             |\n| USDbC  | Base      | 80%        | 79%            | 77%         | 76%             |\n| USDC   | Ethereum  | 80%        | 79%            | 77%         | 76%             |\n| USDT   | Ethereum  | 80%        | 79%            | 77%         | 76%             |\n| DAI    | Ethereum  | 80%        | 79%            | 77%         | 76%             |\n| sDAI   | Ethereum  | 80%        | 79%            | 77%         | 76%             |\n| USDC   | Gnosis    | 80%        | 79%            | 77%         | 76%             |\n| sDAI   | Gnosis    | 80%        | 79%            | 77%         | 76%             |\n| xDAI   | Gnosis    | 80%        | 79%            | 77%         | 76%             |\n| USDC   | Optimism  | 80%        | 79%            | 77%         | 76%             |\n| USDT   | Optimism  | 80%        | 79%            | 77%         | 76%             |\n| USDC.e | Optimism  | 85%        | 84%            | 80%         | 78%             |\n| DAI    | Optimism  | 83%        | 80%            | 78%         | 75%             |\n| USDC   | Polygon   | 80%        | 79%            | 77%         | 76%             |\n| USDT   | Polygon   | 80%        | 79%            | 77%         | 76%             |\n| DAI    | Polygon   | 81%        | 79%            | 76%         | -               |\n| USDC.e | Polygon   | 80%        | 79%            | 77%         | 76%             |\n| USDC   | Scroll    | 80%        | 79%            | 77%         | 76%             |\n\n## References\n\n- Implementation: [AaveV3Ethereum](https://github.com/bgd-labs/aave-proposals-v3/blob/e091a75ca6afed7385f5c0a99829ea5cbdd02442/src/20240324_Multi_GeneralizedLTLTVReductionOnAave/AaveV3Ethereum_GeneralizedLTLTVReductionOnAave_20240324.sol), [AaveV3Polygon](https://github.com/bgd-labs/aave-proposals-v3/blob/e091a75ca6afed7385f5c0a99829ea5cbdd02442/src/20240324_Multi_GeneralizedLTLTVReductionOnAave/AaveV3Polygon_GeneralizedLTLTVReductionOnAave_20240324.sol), [AaveV3Avalanche](https://github.com/bgd-labs/aave-proposals-v3/blob/e091a75ca6afed7385f5c0a99829ea5cbdd02442/src/20240324_Multi_GeneralizedLTLTVReductionOnAave/AaveV3Avalanche_GeneralizedLTLTVReductionOnAave_20240324.sol), [AaveV3Optimism](https://github.com/bgd-labs/aave-proposals-v3/blob/e091a75ca6afed7385f5c0a99829ea5cbdd02442/src/20240324_Multi_GeneralizedLTLTVReductionOnAave/AaveV3Optimism_GeneralizedLTLTVReductionOnAave_20240324.sol), [AaveV3Arbitrum](https://github.com/bgd-labs/aave-proposals-v3/blob/e091a75ca6afed7385f5c0a99829ea5cbdd02442/src/20240324_Multi_GeneralizedLTLTVReductionOnAave/AaveV3Arbitrum_GeneralizedLTLTVReductionOnAave_20240324.sol), [AaveV3Base](https://github.com/bgd-labs/aave-proposals-v3/blob/e091a75ca6afed7385f5c0a99829ea5cbdd02442/src/20240324_Multi_GeneralizedLTLTVReductionOnAave/AaveV3Base_GeneralizedLTLTVReductionOnAave_20240324.sol), [AaveV3Gnosis](https://github.com/bgd-labs/aave-proposals-v3/blob/e091a75ca6afed7385f5c0a99829ea5cbdd02442/src/20240324_Multi_GeneralizedLTLTVReductionOnAave/AaveV3Gnosis_GeneralizedLTLTVReductionOnAave_20240324.sol), [AaveV3BNB](https://github.com/bgd-labs/aave-proposals-v3/blob/e091a75ca6afed7385f5c0a99829ea5cbdd02442/src/20240324_Multi_GeneralizedLTLTVReductionOnAave/AaveV3BNB_GeneralizedLTLTVReductionOnAave_20240324.sol), [AaveV3Scroll](https://github.com/bgd-labs/aave-proposals-v3/blob/e091a75ca6afed7385f5c0a99829ea5cbdd02442/src/20240324_Multi_GeneralizedLTLTVReductionOnAave/AaveV3Scroll_GeneralizedLTLTVReductionOnAave_20240324.sol)\n- Tests: [AaveV3Ethereum](https://github.com/bgd-labs/aave-proposals-v3/blob/e091a75ca6afed7385f5c0a99829ea5cbdd02442/src/20240324_Multi_GeneralizedLTLTVReductionOnAave/AaveV3Ethereum_GeneralizedLTLTVReductionOnAave_20240324.t.sol), [AaveV3Polygon](https://github.com/bgd-labs/aave-proposals-v3/blob/e091a75ca6afed7385f5c0a99829ea5cbdd02442/src/20240324_Multi_GeneralizedLTLTVReductionOnAave/AaveV3Polygon_GeneralizedLTLTVReductionOnAave_20240324.t.sol), [AaveV3Avalanche](https://github.com/bgd-labs/aave-proposals-v3/blob/e091a75ca6afed7385f5c0a99829ea5cbdd02442/src/20240324_Multi_GeneralizedLTLTVReductionOnAave/AaveV3Avalanche_GeneralizedLTLTVReductionOnAave_20240324.t.sol), [AaveV3Optimism](https://github.com/bgd-labs/aave-proposals-v3/blob/e091a75ca6afed7385f5c0a99829ea5cbdd02442/src/20240324_Multi_GeneralizedLTLTVReductionOnAave/AaveV3Optimism_GeneralizedLTLTVReductionOnAave_20240324.t.sol), [AaveV3Arbitrum](https://github.com/bgd-labs/aave-proposals-v3/blob/e091a75ca6afed7385f5c0a99829ea5cbdd02442/src/20240324_Multi_GeneralizedLTLTVReductionOnAave/AaveV3Arbitrum_GeneralizedLTLTVReductionOnAave_20240324.t.sol), [AaveV3Base](https://github.com/bgd-labs/aave-proposals-v3/blob/e091a75ca6afed7385f5c0a99829ea5cbdd02442/src/20240324_Multi_GeneralizedLTLTVReductionOnAave/AaveV3Base_GeneralizedLTLTVReductionOnAave_20240324.t.sol), [AaveV3Gnosis](https://github.com/bgd-labs/aave-proposals-v3/blob/e091a75ca6afed7385f5c0a99829ea5cbdd02442/src/20240324_Multi_GeneralizedLTLTVReductionOnAave/AaveV3Gnosis_GeneralizedLTLTVReductionOnAave_20240324.t.sol), [AaveV3BNB](https://github.com/bgd-labs/aave-proposals-v3/blob/e091a75ca6afed7385f5c0a99829ea5cbdd02442/src/20240324_Multi_GeneralizedLTLTVReductionOnAave/AaveV3BNB_GeneralizedLTLTVReductionOnAave_20240324.t.sol), [AaveV3Scroll](https://github.com/bgd-labs/aave-proposals-v3/blob/e091a75ca6afed7385f5c0a99829ea5cbdd02442/src/20240324_Multi_GeneralizedLTLTVReductionOnAave/AaveV3Scroll_GeneralizedLTLTVReductionOnAave_20240324.t.sol)\n- [Snapshot](https://snapshot.org/#/aave.eth/proposal/0x4067d91ef5864925136d10ec9419f032a70f7e6489740386e348488426656274)\n- [Discussion](https://governance.aave.com/t/generalized-lt-ltv-reduction-on-aave/16766)\n\n## Copyright\n\nCopyright and related rights waived via [CC0](https://creativecommons.org/publicdomain/zero/1.0/).\n",
    "title": "Generalized LT/LTV Reduction on Aave",
    "author": "Chaos Labs",
    "discussions": "https://governance.aave.com/t/generalized-lt-ltv-reduction-on-aave/16766",
    "snapshot": "https://snapshot.org/#/aave.eth/proposal/0x4067d91ef5864925136d10ec9419f032a70f7e6489740386e348488426656274",
    "originalIpfsHash": "0x293815b30e809a40f094c7a6164a60bc5d306cc915455bbbfb1c083fd1161f1d"
  },
  "proposal": {
    "id": 71,
    "votingDuration": 259200,
    "creationTime": 1712351807,
    "accessLevel": 1,
    "state": 4,
    "queuingTime": 1712699675,
    "ipfsHash": "0x293815b30e809a40f094c7a6164a60bc5d306cc915455bbbfb1c083fd1161f1d",
    "initialPayloads": [
      {
        "id": 98,
        "chainId": 1,
        "payloadsController": "0xdAbad81aF85554E9ae636395611C58F7eC1aAEc5"
      },
      {
        "id": 51,
        "chainId": 137,
        "payloadsController": "0x401B5D0294E23637c18fcc38b1Bca814CDa2637C"
      },
      {
        "id": 22,
        "chainId": 43114,
        "payloadsController": "0x1140CB7CAfAcC745771C2Ea31e7B5C653c5d0B80"
      },
      {
        "id": 24,
        "chainId": 10,
        "payloadsController": "0x0E1a3Af1f9cC76A62eD31eDedca291E63632e7c4"
      },
      {
        "id": 23,
        "chainId": 42161,
        "payloadsController": "0x89644CA1bB8064760312AE4F03ea41b05dA3637C"
      },
      {
        "id": 16,
        "chainId": 8453,
        "payloadsController": "0x2DC219E716793fb4b21548C0f009Ba3Af753ab01"
      },
      {
        "id": 12,
        "chainId": 100,
        "payloadsController": "0x9A1F491B86D09fC1484b5fab10041B189B60756b"
      },
      {
        "id": 10,
        "chainId": 56,
        "payloadsController": "0xE5EF2Dd06755A97e975f7E282f828224F2C3e627"
      },
      {
        "id": 8,
        "chainId": 534352,
        "payloadsController": "0x6b6B41c0f8C223715f712BE83ceC3c37bbfDC3fE"
      }
    ],
    "snapshotBlockHash": "0xd3b091b3fa150a25ab4b2ef7e8b1c21b87926443b4d97f47c19685e17305a594",
    "creator": "0x57ab7ee15cE5ECacB1aB84EE42D5A9d0d8112922",
    "canceledAt": 0,
    "votingActivationTime": 1712438231,
    "votingChainId": 137,
    "votingMachineData": {
      "id": 71,
      "forVotes": "536588459260622599857794",
      "againstVotes": "137314310244281916272",
      "startTime": 1712439218,
      "endTime": 1712698418,
      "votingClosedAndSentBlockNumber": 55640787,
      "votingClosedAndSentTimestamp": 1712698427,
      "l1BlockHash": "0xd3b091b3fa150a25ab4b2ef7e8b1c21b87926443b4d97f47c19685e17305a594",
      "strategy": "0x59e6CAD5d7E7b9A26a45a1d1E74C7aF008170042",
      "sentToGovernance": true,
      "createdBlock": 55524747,
      "votedInfo": {
        "support": false,
        "votingPower": "0"
      },
      "votingAssets": [
        "0x7Fc66500c84A76Ad7e9c93437bFc5Ac33E2DDaE9",
        "0x4da27a545c0c5B758a6BA100e3a049001de870f5",
        "0xA700b4eB416Be35b2911fd5Dee80678ff64fF6C9"
      ],
      "hasRequiredRoots": true
    },
    "isFinished": true,
    "lastUpdatedTimestamp": 1714575968,
    "cancellationFee": 50000000000000000
  }
}