{
  "245_0_3_59144": {
    "type": 0,
    "title": "",
    "timestamp": 1738765099,
    "addresses": [
      "0xC89595903010eef079CAE8050ad0166B1DB5B144"
    ],
    "txInfo": {
      "id": 3,
      "hash": "0xba22de77bb4d977373ae14f5124f16f0c055b6148544b0a3534827b8e7858212",
      "chainId": 59144,
      "hashLoading": false
    }
  },
  "245_1": {
    "type": 1,
    "title": "",
    "timestamp": 1738838123,
    "addresses": null,
    "txInfo": {
      "id": 245,
      "hash": "0x62b5a946b2e8d2ca58122acabfb075ce77be27f669f5dd3937dd8e243ac00807",
      "chainId": 1,
      "hashLoading": false
    }
  }
}