{
  "457_0_412_1": {
    "type": 0,
    "title": "",
    "timestamp": 1773404951,
    "addresses": [
      "0xF278dE48F4Fc9C1fB43bD33387301Ccbf774Dc5A"
    ],
    "txInfo": {
      "id": 412,
      "hash": "0x8817920e808687a965af206537c64991b5ca0312ef79847c2389db79baf4a616",
      "chainId": 1,
      "hashLoading": false
    }
  },
  "457_0_110_43114": {
    "type": 0,
    "title": "",
    "timestamp": 1773405132,
    "addresses": [
      "0xc2c7c62e6Ef7Df4fCe0c8E2f3Fec4f3fb14eD995"
    ],
    "txInfo": {
      "id": 110,
      "hash": "0xe830c57c18f1b0dab499004bd621eda2a9ff102487aec6eb59201b48688e679c",
      "chainId": 43114,
      "hashLoading": false
    }
  },
  "457_0_114_42161": {
    "type": 0,
    "title": "",
    "timestamp": 1773405247,
    "addresses": [
      "0x46466E924b4E37602bA2F0386498d39aae865615"
    ],
    "txInfo": {
      "id": 114,
      "hash": "0x40a06c9cf7ffac094d191aa571ec43d8f559f7fa8c250079dae5cc2edc2120fa",
      "chainId": 42161,
      "hashLoading": false
    }
  },
  "457_0_101_8453": {
    "type": 0,
    "title": "",
    "timestamp": 1773405331,
    "addresses": [
      "0xb3A9765D7BC06F1C30CCBD8D7241CdCed80988CB"
    ],
    "txInfo": {
      "id": 101,
      "hash": "0x1588554172eb168a0211872b08963fc5513c76cf074f6a77172191e42c2e91ad",
      "chainId": 8453,
      "hashLoading": false
    }
  },
  "457_0_72_100": {
    "type": 0,
    "title": "",
    "timestamp": 1773405525,
    "addresses": [
      "0x77Be64545b1FF0B464A78F213e8E557D0ee124d5"
    ],
    "txInfo": {
      "id": 72,
      "hash": "0x4898967fd7b93872635faabc5d3c070afdd7c07e333aaf4a293c8ec7378856cb",
      "chainId": 100,
      "hashLoading": false
    }
  },
  "457_0_4_57073": {
    "type": 0,
    "title": "",
    "timestamp": 1773405663,
    "addresses": [
      "0xDB2C74653b9A9b309d6Caff05Ed9Cc33d5F9e50F"
    ],
    "txInfo": {
      "id": 4,
      "hash": "0x220551132b067aa1ae3c9c1c85a75ff98a18e7b8b354a4ea89e66886a5fc7d2e",
      "chainId": 57073,
      "hashLoading": false
    }
  },
  "457_0_3_5000": {
    "type": 0,
    "title": "",
    "timestamp": 1773406070,
    "addresses": [
      "0x415a0D9A165EFE8530A8094b7e05788e5909DAf1"
    ],
    "txInfo": {
      "id": 3,
      "hash": "0x4c8e6425bf1bdc1875896a6dc2e7d450a395f6c9311b5722ace76ba620b0f0ef",
      "chainId": 5000,
      "hashLoading": false
    }
  },
  "457_0_20_9745": {
    "type": 0,
    "title": "",
    "timestamp": 1773406206,
    "addresses": [
      "0x99eEBBf556D866483Cf4f53Af1A16a28dd8085F4"
    ],
    "txInfo": {
      "id": 20,
      "hash": "0x080dba54ec0814c209e4a638eb5df4ec0eebd1b8ad654cb41f800f376b2a76aa",
      "chainId": 9745,
      "hashLoading": false
    }
  },
  "457_0_0_196": {
    "type": 0,
    "title": "",
    "timestamp": 1773407114,
    "addresses": [
      "0x6F0BaBDA7B1Eda822a425Be2963af8E9b912AFc9"
    ],
    "txInfo": {
      "id": 0,
      "hash": "0x37f36118025a71790d42f6eaf05402f74c359c97ae5906688c353d3f3f35e2b2",
      "chainId": 196,
      "hashLoading": false
    }
  },
  "457_1": {
    "type": 1,
    "title": "",
    "timestamp": 1773651863,
    "addresses": null,
    "txInfo": {
      "id": 457,
      "hash": "0xff0deb9d0768a61e80994542543c7c301fad46c0bff0cc2fa9eb801e36af8c08",
      "chainId": 1,
      "hashLoading": false
    }
  },
  "457_2": {
    "type": 2,
    "title": "",
    "timestamp": 1773738299,
    "addresses": null,
    "txInfo": {
      "id": 457,
      "hash": "0x7846e7193746ce68affaa7ed9e5d752833cb6267a017eb07c1b9952f937af4cf",
      "chainId": 1,
      "hashLoading": false
    }
  },
  "457_3": {
    "type": 3,
    "title": "",
    "timestamp": 1773739358,
    "addresses": null,
    "txInfo": {
      "id": 457,
      "hash": "0x0000000000000000000000000000000000000000000000000000000000000000",
      "chainId": 43114,
      "hashLoading": false
    }
  },
  "457_4": {
    "type": 4,
    "title": "",
    "timestamp": 1773998558,
    "addresses": null,
    "txInfo": {
      "id": 457,
      "hash": "0x0000000000000000000000000000000000000000000000000000000000000000",
      "chainId": 43114,
      "hashLoading": false
    }
  },
  "457_5": {
    "type": 5,
    "title": "",
    "timestamp": 1773998564,
    "addresses": null,
    "txInfo": {
      "id": 457,
      "hash": "0x0000000000000000000000000000000000000000000000000000000000000000",
      "chainId": 43114,
      "hashLoading": false
    }
  },
  "457_6": {
    "type": 6,
    "title": "",
    "timestamp": null,
    "addresses": null,
    "txInfo": {
      "id": 457,
      "hash": "0x0000000000000000000000000000000000000000000000000000000000000000",
      "chainId": 1,
      "hashLoading": false
    }
  },
  "457_7": {
    "type": 7,
    "title": "",
    "timestamp": 1773998651,
    "addresses": null,
    "txInfo": {
      "id": 457,
      "hash": "0xe325eef0ab00ad3b3e1346431382a7f33d3c3ef81333247d83af0c51690411b1",
      "chainId": 1,
      "hashLoading": false
    }
  },
  "457_8": {
    "type": 8,
    "title": "",
    "timestamp": 1773998663,
    "addresses": null,
    "txInfo": {
      "id": 457,
      "hash": "0xb58a5ca09155c7d97134928f865d3b09adf43d24bb07aead048798f761006f4b",
      "chainId": 1,
      "hashLoading": false
    }
  },
  "457_9_412_1": {
    "type": 9,
    "title": "",
    "timestamp": 1773998663,
    "addresses": null,
    "txInfo": {
      "id": 412,
      "hash": "0xb58a5ca09155c7d97134928f865d3b09adf43d24bb07aead048798f761006f4b",
      "chainId": 1,
      "hashLoading": false
    }
  },
  "457_9_110_43114": {
    "type": 9,
    "title": "",
    "timestamp": 1773999667,
    "addresses": null,
    "txInfo": {
      "id": 110,
      "hash": "0x717a6bae3996cd832e28351a7aaaacde6f081dbac2282961f5e2b878d866f3f9",
      "chainId": 43114,
      "hashLoading": false
    }
  },
  "457_9_114_42161": {
    "type": 9,
    "title": "",
    "timestamp": 1773999205,
    "addresses": null,
    "txInfo": {
      "id": 114,
      "hash": "0x615d8911337579e302f74a6b21f869ac7efd6cf8583df300f595601b543926bb",
      "chainId": 42161,
      "hashLoading": false
    }
  },
  "457_9_101_8453": {
    "type": 9,
    "title": "",
    "timestamp": 1773998843,
    "addresses": null,
    "txInfo": {
      "id": 101,
      "hash": "0x014a06aff1d2e78f28da03c19972f2e096b1723c6a98465bf0c53c179ab9736b",
      "chainId": 8453,
      "hashLoading": false
    }
  },
  "457_9_72_100": {
    "type": 9,
    "title": "",
    "timestamp": 1774000770,
    "addresses": null,
    "txInfo": {
      "id": 72,
      "hash": "0x170df82020c50cdace02ca20489c2c02eb3168fd6bd7ede2bc6837ec63362ebe",
      "chainId": 100,
      "hashLoading": false
    }
  },
  "457_9_4_57073": {
    "type": 9,
    "title": "",
    "timestamp": 1773998727,
    "addresses": null,
    "txInfo": {
      "id": 4,
      "hash": "0xdffe702ff55f25921fbd5070dbac5f0c862df6042e0f9d4dec1ec93ab107343f",
      "chainId": 57073,
      "hashLoading": false
    }
  },
  "457_9_3_5000": {
    "type": 9,
    "title": "",
    "timestamp": 1773998716,
    "addresses": null,
    "txInfo": {
      "id": 3,
      "hash": "0x51406ec6a7f161dcb1481163308deef474a73e750ba9e2d0de98f0a925ad475f",
      "chainId": 5000,
      "hashLoading": false
    }
  },
  "457_9_20_9745": {
    "type": 9,
    "title": "",
    "timestamp": 1773999628,
    "addresses": null,
    "txInfo": {
      "id": 20,
      "hash": "0xd80fe049e458918588a8c01c3e42b87a0c55c2cf48dd87c83a2c13580ade4d46",
      "chainId": 9745,
      "hashLoading": false
    }
  }
}