{
  "472_0_427_1": {
    "type": 0,
    "title": "",
    "timestamp": 1776099851,
    "addresses": [
      "0x1BBE770bDf9125c218EaBDCdf0252264A226Acdc"
    ],
    "txInfo": {
      "id": 427,
      "hash": "0x77754174375c3e7e7ea2f6d3359bc4b3cdd88626ddb48302e194c7f8f7685d75",
      "chainId": 1,
      "hashLoading": false
    }
  },
  "472_1": {
    "type": 1,
    "title": "",
    "timestamp": 1776160523,
    "addresses": null,
    "txInfo": {
      "id": 472,
      "hash": "0xe9ad0a09219b32df56541ecf6791b0bae4c5c6994a7c41da6b2b8e746a63ebd1",
      "chainId": 1,
      "hashLoading": false
    }
  },
  "472_2": {
    "type": 2,
    "title": "",
    "timestamp": 1776246947,
    "addresses": null,
    "txInfo": {
      "id": 472,
      "hash": "0x0087e8bb0429ee0e8662bd161fb75b4a58e996b902375b8b792917c4c470c578",
      "chainId": 1,
      "hashLoading": false
    }
  },
  "472_3": {
    "type": 3,
    "title": "",
    "timestamp": 1776325780,
    "addresses": null,
    "txInfo": {
      "id": 472,
      "hash": "0x0000000000000000000000000000000000000000000000000000000000000000",
      "chainId": 43114,
      "hashLoading": false
    }
  },
  "472_4": {
    "type": 4,
    "title": "",
    "timestamp": 1776584980,
    "addresses": null,
    "txInfo": {
      "id": 472,
      "hash": "0x0000000000000000000000000000000000000000000000000000000000000000",
      "chainId": 43114,
      "hashLoading": false
    }
  },
  "472_5": {
    "type": 5,
    "title": "",
    "timestamp": 1776584993,
    "addresses": null,
    "txInfo": {
      "id": 472,
      "hash": "0x0000000000000000000000000000000000000000000000000000000000000000",
      "chainId": 43114,
      "hashLoading": false
    }
  },
  "472_6": {
    "type": 6,
    "title": "",
    "timestamp": null,
    "addresses": null,
    "txInfo": {
      "id": 472,
      "hash": "0x0000000000000000000000000000000000000000000000000000000000000000",
      "chainId": 1,
      "hashLoading": false
    }
  },
  "472_7": {
    "type": 7,
    "title": "",
    "timestamp": 1776585071,
    "addresses": null,
    "txInfo": {
      "id": 472,
      "hash": "0x3ef395f837a0b72ce983c839ed77c6f17cff9a7474a05bb36c184ddc42891f68",
      "chainId": 1,
      "hashLoading": false
    }
  },
  "472_8": {
    "type": 8,
    "title": "",
    "timestamp": 1776585107,
    "addresses": null,
    "txInfo": {
      "id": 472,
      "hash": "0x3cfc8250d627bb54606d1adbc1f0638d461c475a0767acebe3909ee1e7e2c162",
      "chainId": 1,
      "hashLoading": false
    }
  },
  "472_9_427_1": {
    "type": 9,
    "title": "",
    "timestamp": 1776585107,
    "addresses": null,
    "txInfo": {
      "id": 427,
      "hash": "0x3cfc8250d627bb54606d1adbc1f0638d461c475a0767acebe3909ee1e7e2c162",
      "chainId": 1,
      "hashLoading": false
    }
  }
}