{
  "229_0_231_1": {
    "type": 0,
    "title": "",
    "timestamp": 1736431583,
    "addresses": [
      "0x0a2A9a20F42e663f4fdC94eE7dA1B0E245D87C1D"
    ],
    "txInfo": {
      "id": 231,
      "hash": "0x7b4e6fdeb00ce499ff9e38fc2bf833cbca8f327081dd8538032d02927276aadc",
      "chainId": 1,
      "hashLoading": false
    }
  },
  "229_1": {
    "type": 1,
    "title": "",
    "timestamp": 1736431727,
    "addresses": null,
    "txInfo": {
      "id": 229,
      "hash": "0xf4971f635f0c923094ec2085c0ee62999b0d0fe39009913d529eedd6c8a364ce",
      "chainId": 1,
      "hashLoading": false
    }
  }
}