{
  "101_0_123_1": {
    "type": 0,
    "title": "",
    "timestamp": 1715104055,
    "addresses": [
      "0xFd6c481111e26DCE6CEfD2909ad0644111B6817f"
    ],
    "txInfo": {
      "id": 123,
      "hash": "0x0000000000000000000000000000000000000000000000000000000000000000",
      "chainId": 1,
      "hashLoading": false
    }
  },
  "101_1": {
    "type": 1,
    "title": "",
    "timestamp": 1715104463,
    "addresses": null,
    "txInfo": {
      "id": 101,
      "hash": "0x0000000000000000000000000000000000000000000000000000000000000000",
      "chainId": 1,
      "hashLoading": false
    }
  },
  "101_11": {
    "type": 11,
    "title": "",
    "timestamp": 1715145851,
    "addresses": null,
    "txInfo": {
      "id": 101,
      "hash": "0x0000000000000000000000000000000000000000000000000000000000000000",
      "chainId": 1,
      "hashLoading": false
    }
  },
  "101_12_123_1": {
    "type": 12,
    "title": "",
    "timestamp": 3433232110,
    "addresses": null,
    "txInfo": {
      "id": 123,
      "hash": "0x0000000000000000000000000000000000000000000000000000000000000000",
      "chainId": 1,
      "hashLoading": false
    }
  }
}